quickdb/__init__.py
quickdb/cli.py
quickdb/cli_entry.py
quickdb/constants.py
quickdb/db.py
quickdb/filedb.py
quickdb/utils.py
quickstore-0.1.1.dist-info/licenses/LICENSE
quickstore-0.1.1.dist-info/METADATA
quickstore-0.1.1.dist-info/WHEEL
quickstore-0.1.1.dist-info/top_level.txt
quickstore-0.1.1.dist-info/RECORD
