Metadata-Version: 2.4
Name: quickstore
Version: 0.1.1
Summary: A developer-friendly, zero-dependency key-value database with TTL, file management, and in-memory search.
Home-page: https://github.com/yourusername/quickstore
Author: Avishek Devnath
Author-email: Avishek Devnath <avishekdevnath@gmail.com>
License: MIT License
Classifier: Programming Language :: Python :: 3
Classifier: License :: OSI Approved :: MIT License
Classifier: Operating System :: OS Independent
Requires-Python: >=3.6
License-File: LICENSE
Dynamic: author
Dynamic: home-page
Dynamic: license-file
Dynamic: requires-python
